mocap_sync/__init__.py
mocap_sync/axengine_1755252324_223009110.py
mocap_sync/operations/__init__.py
mocap_sync/operations/opsInputVideosAudios.py
mocap_sync/operations/opsSyncMultiviewVideos.py
mocap_sync/syncing/__init__.py
mocap_sync/syncing/metadata_log.py
mocap_sync/syncing/smoother.py
mocap_sync/syncing/sync_crop_from_txt.py
mocap_sync/syncing/sync_iphones.py
mocap_sync/syncing/sync_multi_video.py
mocap_sync/syncing/sync_multi_video_manual.py
mocap_sync/syncing/sync_visually.py
mocap_sync/syncing/syncing_app.py
mocap_sync/syncing/syncing_app_v2.py
mocap_sync/syncing/test.py
mocap_sync/syncing/util.py
mocap_sync/syncing/vis_syncing.py
mocap_sync-2.3.0.dist-info/METADATA
mocap_sync-2.3.0.dist-info/WHEEL
mocap_sync-2.3.0.dist-info/RECORD
